cdklabs/cdk_cicd_wrapper/__init__.py
cdklabs/cdk_cicd_wrapper/py.typed
cdklabs/cdk_cicd_wrapper/_jsii/__init__.py
cdklabs/cdk_cicd_wrapper/_jsii/cdk-cicd-wrapper@0.3.2.jsii.tgz
cdklabs_cdk_cicd_wrapper-0.3.2.dist-info/LICENSE
cdklabs_cdk_cicd_wrapper-0.3.2.dist-info/METADATA
cdklabs_cdk_cicd_wrapper-0.3.2.dist-info/WHEEL
cdklabs_cdk_cicd_wrapper-0.3.2.dist-info/top_level.txt
cdklabs_cdk_cicd_wrapper-0.3.2.dist-info/RECORD
