Metadata-Version: 2.1
Name: cdklabs.cdk-cicd-wrapper
Version: 0.3.2
Summary: This repository contains the infrastructure as code to wrap your AWS CDK project with CI/CD around it.
Home-page: https://github.com/cdklabs/cdk-cicd-wrapper.git
Author: CDK CI/CD Wrapper Team
License: Apache-2.0
Project-URL: Source, https://github.com/cdklabs/cdk-cicd-wrapper.git
Classifier: Intended Audience :: Developers
Classifier: Operating System :: OS Independent
Classifier: Programming Language :: JavaScript
Classifier: Programming Language :: Python :: 3 :: Only
Classifier: Programming Language :: Python :: 3.9
Classifier: Programming Language :: Python :: 3.10
Classifier: Programming Language :: Python :: 3.11
Classifier: Typing :: Typed
Classifier: Development Status :: 5 - Production/Stable
Classifier: License :: OSI Approved
Requires-Python: ~=3.9
License-File: LICENSE
Requires-Dist: aws-cdk-lib <3.0.0,>=2.195.0
Requires-Dist: cdk-nag <3.0.0,>=2.28.0
Requires-Dist: cdk-pipelines-github <0.5.0,>=0.4.132
Requires-Dist: constructs <11.0.0,>=10.3.0
Requires-Dist: jsii <2.0.0,>=1.115.0
Requires-Dist: publication >=0.0.3
Requires-Dist: typeguard <4.3.0,>=2.13.3
